finetune_eval
